imgdups/__init__.py
imgdups/imgdups.py
imgdups-0.1.6.dist-info/LICENSE
imgdups-0.1.6.dist-info/METADATA
imgdups-0.1.6.dist-info/WHEEL
imgdups-0.1.6.dist-info/entry_points.txt
imgdups-0.1.6.dist-info/top_level.txt
imgdups-0.1.6.dist-info/zip-safe
imgdups-0.1.6.dist-info/RECORD
